{
    "asset_types": {
        "domestic_equity": {
            "name": "Equity",
            "icon": "/assets/stock.png",
            "color": "pink"
        },
        "gold": {
            "name": "Gold",
            "icon": "/assets/gold.png",
            "color": "yellow"
        },
        "crypto": {
            "name": "Crypto",
            "icon": "/assets/crypto.png",
            "color": "teal"
        },
        "debt": {
            "name": "Debt",
            "icon": "/assets/debt.png",
            "color": "indigo"
        },
        "us_equity": {
            "name": "US Equity",
            "icon": "/assets/us_equity.png",
            "color": "orange"
        },
        "real_estate": {
            "name": "Real Estate",
            "icon": "/assets/real_estate.png",
            "color": "purple"
        }
    }
}